Workbook
Name image: #REF!

Sheet CULTURA
Z2: TOTALES | AE2: %
C3: INSTITUCIÓN: | E3: OLEA CONTROLS MEXICO | Z3: RESULTADOS | AC3: 1 | AD3: 1 | AE3: =+AVERAGE(AJ:AJ) -> 0.68965517
C5: COLABORADOR: | E5: ROSA AMALIA ARZA MARTINEZ
C7: CARGO: | E7: SERVICIO A CLIENTES | Q7: AÑO | S7: 2025 | V7: =+EOMONTH(E11,0) -> 45991 | W7: =+COUNTIF($E$12:$AI$12,"S")+COUNTIF($E$12:$AI$12,"D") -> 10
C9: PERIODO: | Q9: MES | S9: Noviembre | V9: =+VLOOKUP(S9,Hoja2!$A$1:$B$12,2,FALSE) -> 11 | W9: =+DAY(V7) -> 30
AK10: 0 | AL10: T | AM10: J
E11: =+E13&"/"&$V$9&"/"&$S$7 -> 1/11/2025 | F11: =+F13&"/"&$V$9&"/"&$S$7 -> 2/11/2025 | G11: =+G13&"/"&$V$9&"/"&$S$7 -> 3/11/2025 | H11: =+H13&"/"&$V$9&"/"&$S$7 -> 4/11/2025 | I11: =+I13&"/"&$V$9&"/"&$S$7 -> 5/11/2025 | J11: =+J13&"/"&$V$9&"/"&$S$7 -> 6/11/2025 | K11: =+K13&"/"&$V$9&"/"&$S$7 -> 7/11/2025 | L11: =+L13&"/"&$V$9&"/"&$S$7 -> 8/11/2025 | ... AI11: =+AI13&"/"&$V$9&"/"&$S$7 -> /11/2025 | AJ11: RESULTADOS
E12: =+IFERROR(VLOOKUP(WEEKDAY(E11,2),Hoja2!$D$1:$E$7,2,FALSE),"") -> S | F12: =+IFERROR(VLOOKUP(WEEKDAY(F11,2),Hoja2!$D$1:$E$7,2,FALSE),"") -> D | G12: =+IFERROR(VLOOKUP(WEEKDAY(G11,2),Hoja2!$D$1:$E$7,2,FALSE),"") -> L | H12: =+IFERROR(VLOOKUP(WEEKDAY(H11,2),Hoja2!$D$1:$E$7,2,FALSE),"") -> M | I12: =+IFERROR(VLOOKUP(WEEKDAY(I11,2),Hoja2!$D$1:$E$7,2,FALSE),"") -> M | J12: =+IFERROR(VLOOKUP(WEEKDAY(J11,2),Hoja2!$D$1:$E$7,2,FALSE),"") -> J | K12: =+IFERROR(VLOOKUP(WEEKDAY(K11,2),Hoja2!$D$1:$E$7,2,FALSE),"") -> V | L12: =+IFERROR(VLOOKUP(WEEKDAY(L11,2),Hoja2!$D$1:$E$7,2,FALSE),"") -> S | ... AI12: =+IFERROR(VLOOKUP(WEEKDAY(AI11,2),Hoja2!$D$1:$E$7,2,FALSE),"")
B13: NO | C13: CONCEPTO | E13: 1 | F13: =+IF((E13+1)<=$W$9,(E13+1),"") -> 2 | G13: =+IF((F13+1)<=$W$9,(F13+1),"") -> 3 | H13: =+IF((G13+1)<=$W$9,(G13+1),"") -> 4 | I13: =+IF((H13+1)<=$W$9,(H13+1),"") -> 5 | J13: =+IF((I13+1)<=$W$9,(I13+1),"") -> 6 | K13: =+IF((J13+1)<=$W$9,(J13+1),"") -> 7 | L13: =+IF((K13+1)<=$W$9,(K13+1),"") -> 8 | M13: =+IF((L13+1)<=$W$9,(L13+1),"") -> 9 | ... AI13: =+IF((AH13+1)<=$W$9,(AH13+1),"")
B15: 1 | C15: Club 6am | G15: 1 | H15: 1 | I15: 1 | J15: 1 | K15: 1 | AJ15: =SUM(E15:AH15) -> 5
B16: 2 | C16: Gigas ilimitados celular | K16: 1 | AJ16: =SUM(E16:AH16) -> 1
B17: 3 | C17: Meta alcanzada | AJ17: =SUM(E17:AH17) -> 0
B18: 4 | C18: Gimnasio (comprobante mensual) | I18: 1 | P18: 0 | AJ18: =SUM(E18:AH18) -> 1
B19: 5 | C19: Limpieza dental (comprobante semestral) | J19: 0 | Q19: 0 | AJ19: =SUM(E19:AH19) -> 0
B20: 6 | C20: Lectura Reto libro | AJ20: =SUM(E20:AH20) -> 0
B21: 7 | C21: Consulta médica Preventiva - CMP | AJ21: =SUM(E21:AH21) -> 0
B22: 8 | C22: Consúlta Psicológica Preventiva- CPP | AJ22: =SUM(E22:AH22) -> 0
B23: 9 | C23: Consúlta Psicológica Preventiva- CPP | G23: 1 | I23: 1 | AJ23: =SUM(E23:AH23) -> 2
B24: 10 | C24: Comisión por imagen personal | AJ24: =SUM(E24:AH24) -> 0
B25: 11 | C25: Comisión por cuidar herramientas | J25: 1 | N25: 1 | AJ25: =SUM(E25:AH25) -> 2
B26: 12 | C26: Comi por llevar herramientas | AJ26: =SUM(E26:AH26) -> 0
B27: DEDUCCCIONES
B28: 14 | C28: ProEx | G28: 1 | H28: 1 | AJ28: =SUM(E28:AH28) -> 2
B29: 15 | C29: M.A.D. | H29: 1 | AJ29: =SUM(E29:AH29) -> 1
B30: 16 | C30: S. Gumby | G30: 1 | AJ30: =SUM(E30:AH30) -> 1
B31: 17 | C31: Humildad | AJ31: =SUM(E31:AH31) -> 0
B32: 18 | C32: La Panoramización | H32: 1 | AJ32: =SUM(E32:AH32) -> 1
B33: 19 | C33: La Auditoría | AJ33: =SUM(E33:AH33) -> 0
B34: 20 | C34: La Reiteración | I34: 1 | AJ34: =SUM(E34:AH34) -> 1
B35: 21 | C35: ZAPES | AJ35: =SUM(E35:AH35) -> 0
B36: 22 | C36: Ciclo OODA | J36: 1 | AJ36: =SUM(E36:AH36) -> 1
B37: 23 | C37: S.T.D. | AJ37: =SUM(E37:AH37) -> 0
B38: 24 | C38: Visualización | AJ38: =SUM(E38:AH38) -> 0
B39: 25 | C39: Respiración | AJ39: =SUM(E39:AH39) -> 0
B40: 26 | C40: MiMMOOTs | AJ40: =SUM(E40:AH40) -> 0
B41: 27 | C41: Positividad | P41: 1 | AJ41: =SUM(E41:AH41) -> 1
B42: 28 | C42: Código de Honor-CDH | J42: 1 | AJ42: =SUM(E42:AH42) -> 1
B43: 29 | C43: Zoho FSM | AJ43: =SUM(E43:AH43) -> 0
AJ44: =SUM(E44:AH44) -> 0

Sheet RECIBO
I3: RECIBO DE NOMINA
B6: INFORMACIÓN DEL COLABORADOR
C9: NOMBRE | E9: ARZA MARTINEZ ROSA AMALIA | I9: ID DEL EMPLEADO | K9: AAMR860816
C11: PUESTO | E11: EJECUTIVO SERVICIO A CLIENTES | I11: PERÍODO DE DECLARACIÓN | K11: 16 al 31 de Agosto 2025
C13: NÚM. DE SEGURIDAD SOCIAL | E13: 45118617450 | I13: FECHA DE PAGO | K13: 45900
B15: INGRESOS
C18: PAGO | I18: DEDUCCIONES
C19: SUELDO | D19: SDI | E19: DIAS | F19: INGRESOS | G19: HASTA LA FECHA | I19: IMPUESTOS | K19: COSTO | L19: DIAS | M19: APLICACIÓN
C20: 6000 | D20: =C20/15 -> 400 | E20: 15 | F20: =E20*D20 -> 6000 | G20: =K13 -> 45900 | I20: ISR | K20: =F20*0.076 -> 456 | L20: N/A | M20: =K20 -> 456
C21: BONIFICACIONES | I21: IMPUESTO ESTATAL | K21: =F20*0.02 -> 120 | L21: N/A | M21: =K21 -> 120
C22: CONCEPTO | E22: DIAS | F22: COSTO | G22: APLICACIÓN | I22: IMPUESTO DE SEGURIDAD SOCIAL | K22: =F20*0.0256 -> 153.6 | L22: N/A | M22: =K22 -> 153.6
C23: Club 6am | E23: =CULTURA!AJ15 -> 5 | F23: 39.47 | G23: =F23*E23 -> 197.35 | I23: ESCARMIENTOS
C24: Gigas ilimitados celular | E24: =CULTURA!AJ16 -> 1 | F24: 9.87 | G24: =F24*E24 -> 9.87 | I24: ProEx | K24: 22 | L24: =CULTURA!AJ28 -> 2 | M24: =K24*L24 -> 44
C25: Consulta médica (solo en caso de estar cumpliendo con su deber) | E25: 1 | F25: 0 | G25: =F25*E25 -> 0 | I25: M.A.D. | K25: 7 | L25: =CULTURA!AJ29 -> 1 | M25: =K25*L25 -> 7
C26: Capacitación Según logros | E26: 1 | F26: 0 | G26: =F26*E26 -> 0 | I26: S. Gumby | K26: 7 | L26: =CULTURA!AJ30 -> 1 | M26: =K26*L26 -> 7
C27: INCENTIVOS | I27: Humildad | K27: 7 | L27: =CULTURA!AJ31 -> 0 | M27: =K27*L27 -> 0
C28: Meta alcanzada | E28: =CULTURA!AJ17 -> 0 | F28: 22 | G28: =F28*E28 -> 0 | I28: La Panoramización | K28: 5 | L28: =CULTURA!AJ32 -> 1 | M28: =K28*L28 -> 5
C29: Recomendación para que cotice un cliente | E29: 1 | G29: =F29*E29 -> 0 | I29: La Auditoría | K29: 5 | L29: =CULTURA!AJ33 -> 0 | M29: =K29*L29 -> 0
C30: Gimnasio (comprobante mensual) | E30: =CULTURA!AJ18 -> 1 | F30: 18.09 | G30: =F30*E30 -> 18.09 | I30: La Reiteración | K30: 3 | L30: =CULTURA!AJ34 -> 1 | M30: =K30*L30 -> 3
C31: Limpieza dental (comprobante semestral) | E31: =CULTURA!AJ19 -> 0 | F31: 6.58 | G31: =F31*E31 -> 0 | I31: ZAPES | K31: 9 | L31: =CULTURA!AJ35 -> 0 | M31: =K31*L31 -> 0
C32: Lectura Reto libro | E32: =CULTURA!AJ20 -> 0 | F32: 18.09 | G32: =F32*E32 -> 0 | I32: Ciclo OODA | K32: 9 | L32: =CULTURA!AJ36 -> 1 | M32: =K32*L32 -> 9
C33: Consulta médica Preventiva - CMP | E33: =CULTURA!AJ21 -> 0 | F33: 21.38 | G33: =F33*E33 -> 0 | I33: S.T.D. | K33: 6 | L33: =CULTURA!AJ37 -> 0 | M33: =K33*L33 -> 0
C34: Consúlta Psicológica Preventiva- CPP | E34: =CULTURA!AJ22 -> 0 | F34: 21.31 | G34: =F34*E34 -> 0 | I34: Visualización | K34: 22 | L34: =CULTURA!AJ38 -> 0 | M34: =K34*L34 -> 0
C35: Consúlta Psicológica Preventiva- CPP | E35: =CULTURA!AJ23 -> 2 | F35: 21.31 | G35: =F35*E35 -> 42.62 | I35: Respiración | K35: 22 | L35: =CULTURA!AJ39 -> 0 | M35: =K35*L35 -> 0
C36: COMISIONES | I36: MiMMOOTs | K36: 22 | L36: =CULTURA!AJ40 -> 0 | M36: =K36*L36 -> 0
C37: Comisión por imagen personal | E37: =CULTURA!AJ24 -> 0 | F37: 11 | G37: =F37*E37 -> 0 | I37: Positividad | K37: 22 | L37: =CULTURA!AJ41 -> 1 | M37: =K37*L37 -> 22
C38: Comisión por cuidar herramientas | E38: =CULTURA!AJ25 -> 2 | F38: 5.5 | G38: =F38*E38 -> 11 | I38: Código de Honor-CDH | K38: 33 | L38: =CULTURA!AJ42 -> 1 | M38: =K38*L38 -> 33
C39: Comi por llevar herramientas | E39: =CULTURA!AJ26 -> 0 | F39: 5.5 | G39: =F39*E39 -> 0 | I39: Zoho FSM | K39: 9 | L39: =CULTURA!AJ43 -> 0 | M39: =K39*L39 -> 0
C40: Com. por cerrar la venta 1% | E40: 0 | F40: 3500 | G40: =F40*0.01*E40 -> 0
C42: PRESTACIONES
C43: TIPO | D43: SDI | E43: DIAS APLICADOS | F43: IMPORTE
C44: TIEMPO EXTRA | D44: =F20/15 -> 400 | E44: 0 | F44: =E44*D44 -> 0
C46: INGRESOS BRUTOS | E46: =F20+G23+G24+G25+G26+G28+G29+G30+G31+G32+G33+G34+G35+G37+G38+G39+G40+F44 -> 6278.93 | I46: TOTAL DE DEDUCCIONES | K46: =SUM(M20:M39) -> 859.6
B48: TOTAL
C51: COMENTARIOS: | J51: TOTAL
J52: BRUTO | L52: =E46 -> 6278.93
J53: DEDUCCIONES | L53: =K46 -> 859.6
J54: NETO | L54: =L52-L53 -> 5419.33
J56: NETO TOTAL
J57: =L54 -> 5419.33

Sheet Hoja2
A1: Enero | B1: =+ROW() -> 1 | D1: 1 | E1: L
A2: Febrero | B2: =+ROW() -> 2 | D2: 2 | E2: M
A3: Marzo | B3: =+ROW() -> 3 | D3: 3 | E3: M
A4: Abril | B4: =+ROW() -> 4 | D4: 4 | E4: J
A5: Mayo | B5: =+ROW() -> 5 | D5: 5 | E5: V
A6: Junio | B6: =+ROW() -> 6 | D6: 6 | E6: S
A7: Julio | B7: =+ROW() -> 7 | D7: 7 | E7: D
A8: Agosto | B8: =+ROW() -> 8
A9: Septiembre | B9: =+ROW() -> 9
A10: Octubre | B10: =+ROW() -> 10
A11: Noviembre | B11: =+ROW() -> 11
A12: Diciembre | B12: =+ROW() -> 12
